circuits/xnor_gate.v
// xnor_gate.v

module xnor_gate (
    input wire [3:0] a,
    input wire [3:0] b,
    output wire [3:0] y
);
    assign y = ~(a ^ b); // 4-bit XNOR operation
endmodule

circuits/nor_gate.v
// nor_gate.v
module nor_gate (
    input wire [3:0] a,
    input wire [3:0] b,
    output wire [3:0] y
);
    assign y = ~(a | b);
endmodule

circuits/nand_gate.v
// nand_gate.v
module nand_gate (
    input wire [3:0] a,
    input wire [3:0] b,
    output wire [3:0] y
);
    assign y = ~(a & b);  // Vectorized NAND operation
endmodule

circuits/xor_gate.v
// xor_gate.v
module xor_gate (
    input wire [3:0] a,
    input wire [3:0] b,
    output wire [3:0] y
);
    assign y = a ^ b;  // Perform bitwise XOR operation
endmodule

circuits/or_gate.v
// or_gate.v

module or_gate (
    input wire [3:0] a,
    input wire [3:0] b,
    output wire [3:0] y
);
    assign y = a | b; // 4-bit OR operation
endmodule

circuits/and_gate.v
// and_gate.v
module and_gate (
    input wire [3:0] a,
    input wire [3:0] b,
    output wire [3:0] y
);
    assign y = a & b;
endmodule

circuits/division.v
// division.v
module division (
    input wire [3:0] numerator,
    input wire [3:0] denominator,
    output wire [3:0] quotient,
    output wire [3:0] remainder
);
    assign quotient = denominator != 0 ? numerator / denominator : 0;
    assign remainder = denominator != 0 ? numerator % denominator : 0;
endmodule

circuits/multiplication.v
// multiplication.v
module multiplication (
    input wire [3:0] a,
    input wire [3:0] b,
    output wire [7:0] product  // 8-bit product for multiplication
);
    assign product = a * b;
endmodule

circuits/subtraction.v
// subtraction.v
module subtraction (
    input wire [3:0] a,
    input wire [3:0] b,
    input wire carry_in,
    output wire [3:0] difference,
    output wire carry_out
);
    assign {carry_out, difference} = a - b - {3'b000, carry_in};  // Extend carry_in to 4 bits
endmodule

circuits/addition.v
// addition.v
module addition (
    input wire [3:0] a,
    input wire [3:0] b,
    input wire carry_in,
    output wire [3:0] sum,
    output wire carry_out
);
    assign {carry_out, sum} = a + b + {3'b000, carry_in};  // Extend carry_in to 4 bits
endmodule

circuits/alu.v
module alu (
    input wire [3:0] a,
    input wire [3:0] b,
    input wire [3:0] op_code,
    input wire carry_in,
    output reg [3:0] result,
    output reg carry_out = 0
);
    wire [3:0] add_out, sub_out, div_out, div_rem;
    wire [3:0] and_out, or_out, xor_out, nand_out, nor_out, xnor_out;
    wire [7:0] mul_out;  // 8-bit result for multiplication
    wire [3:0] unused_mul_bits;  // Dummy wire for unused bits
    wire add_carry, sub_carry;

    // Assign unused higher bits of mul_out
    assign unused_mul_bits = mul_out[7:4];  // Explicitly assign unused bits

    // Arithmetic modules
    addition add(.a(a), .b(b), .carry_in(carry_in), .sum(add_out), .carry_out(add_carry));
    subtraction sub(.a(a), .b(b), .carry_in(carry_in), .difference(sub_out), .carry_out(sub_carry));
    multiplication mul(.a(a), .b(b), .product(mul_out));
    division div(.numerator(a), .denominator(b), .quotient(div_out), .remainder(div_rem));

    // Logic modules
    and_gate and_gate_instance(.a(a), .b(b), .y(and_out));
    or_gate or_gate_instance(.a(a), .b(b), .y(or_out));
    xor_gate xor_gate_instance(.a(a), .b(b), .y(xor_out));
    nand_gate nand_gate_instance(.a(a), .b(b), .y(nand_out));
    nor_gate nor_gate_instance(.a(a), .b(b), .y(nor_out));
    xnor_gate xnor_gate_instance(.a(a), .b(b), .y(xnor_out));

    always @(*) begin
        carry_out = 0;
        case (op_code[3:2])
            2'b00:
                case (op_code[1:0])
                    2'b00: {carry_out, result} = {add_carry, add_out};
                    2'b01: {carry_out, result} = {sub_carry, sub_out};
                    2'b10: result = mul_out[3:0];  // Using only lower 4 bits
                    2'b11: result = div_out;
                endcase
            2'b01:
                case (op_code[1:0])
                    2'b00: result = and_out;
                    2'b01: result = or_out;
                    2'b10: result = xor_out;
                    2'b11: result = nand_out;
                endcase
            2'b10:
                case (op_code[1:0])
                    2'b00: result = nor_out;
                    2'b01: result = xnor_out;
                    2'b10: result = div_rem;
                    2'b11: result = 4'b0000;  // Placeholder for unused operation
                endcase
            default: result = 4'b0000;  // Safety default
        endcase
    end
endmodule

waveforms/alu_waveform.vcd
$version Generated by VerilatedVcd $end
$timescale 1ps $end
 $scope module TOP $end
  $var wire 4 ) a [3:0] $end
  $var wire 4 * b [3:0] $end
  $var wire 4 + op_code [3:0] $end
  $var wire 1 , carry_in $end
  $var wire 4 - result [3:0] $end
  $var wire 1 . carry_out $end
  $scope module alu $end
   $var wire 4 ) a [3:0] $end
   $var wire 4 * b [3:0] $end
   $var wire 4 + op_code [3:0] $end
   $var wire 1 , carry_in $end
   $var wire 4 - result [3:0] $end
   $var wire 1 . carry_out $end
   $var wire 4 / add_out [3:0] $end
   $var wire 4 0 sub_out [3:0] $end
   $var wire 4 1 div_out [3:0] $end
   $var wire 4 2 div_rem [3:0] $end
   $var wire 4 # and_out [3:0] $end
   $var wire 4 $ or_out [3:0] $end
   $var wire 4 % xor_out [3:0] $end
   $var wire 4 & nand_out [3:0] $end
   $var wire 4 ' nor_out [3:0] $end
   $var wire 4 ( xnor_out [3:0] $end
   $var wire 8 3 mul_out [7:0] $end
   $var wire 4 4 unused_mul_bits [3:0] $end
   $var wire 1 5 add_carry $end
   $var wire 1 6 sub_carry $end
   $scope module add $end
    $var wire 4 ) a [3:0] $end
    $var wire 4 * b [3:0] $end
    $var wire 1 , carry_in $end
    $var wire 4 / sum [3:0] $end
    $var wire 1 5 carry_out $end
   $upscope $end
   $scope module and_gate_instance $end
    $var wire 4 ) a [3:0] $end
    $var wire 4 * b [3:0] $end
    $var wire 4 # y [3:0] $end
   $upscope $end
   $scope module div $end
    $var wire 4 ) numerator [3:0] $end
    $var wire 4 * denominator [3:0] $end
    $var wire 4 1 quotient [3:0] $end
    $var wire 4 2 remainder [3:0] $end
   $upscope $end
   $scope module mul $end
    $var wire 4 ) a [3:0] $end
    $var wire 4 * b [3:0] $end
    $var wire 8 3 product [7:0] $end
   $upscope $end
   $scope module nand_gate_instance $end
    $var wire 4 ) a [3:0] $end
    $var wire 4 * b [3:0] $end
    $var wire 4 & y [3:0] $end
   $upscope $end
   $scope module nor_gate_instance $end
    $var wire 4 ) a [3:0] $end
    $var wire 4 * b [3:0] $end
    $var wire 4 ' y [3:0] $end
   $upscope $end
   $scope module or_gate_instance $end
    $var wire 4 ) a [3:0] $end
    $var wire 4 * b [3:0] $end
    $var wire 4 $ y [3:0] $end
   $upscope $end
   $scope module sub $end
    $var wire 4 ) a [3:0] $end
    $var wire 4 * b [3:0] $end
    $var wire 1 , carry_in $end
    $var wire 4 0 difference [3:0] $end
    $var wire 1 6 carry_out $end
   $upscope $end
   $scope module xnor_gate_instance $end
    $var wire 4 ) a [3:0] $end
    $var wire 4 * b [3:0] $end
    $var wire 4 ( y [3:0] $end
   $upscope $end
   $scope module xor_gate_instance $end
    $var wire 4 ) a [3:0] $end
    $var wire 4 * b [3:0] $end
    $var wire 4 % y [3:0] $end
   $upscope $end
  $upscope $end
 $upscope $end
$enddefinitions $end


#0
b0001 #
b0111 $
b0110 %
b1110 &
b1000 '
b1001 (
b0101 )
b0011 *
b0000 +
0,
b1000 -
0.
b1000 /
b0010 0
b0001 1
b0010 2
b00001111 3
b0000 4
05
06
#10
b0001 +
b0010 -
#20
b0010 +
b1111 -
#30
b0011 +
b0001 -
#40
b0100 +
#50
b0101 +
b0111 -
#60
b0110 +
b0110 -
#70
b0111 +
b1110 -
#80
b1000 +
b1000 -
#90
b1001 +
b1001 -
#100
b1010 +
b0010 -
#110
b1011 +
b0000 -
#120
b1100 +
#130
b1101 +
#140
b1110 +
#150
b1111 +
